napari_patchcreator/__init__.py
napari_patchcreator/_patch_widget.py
napari_patchcreator/_version.py
napari_patchcreator/napari.yaml
napari_patchcreator/_tests/__init__.py
napari_patchcreator/_tests/test_patch_widget.py
napari_patchcreator-0.1.4.dist-info/LICENSE
napari_patchcreator-0.1.4.dist-info/METADATA
napari_patchcreator-0.1.4.dist-info/WHEEL
napari_patchcreator-0.1.4.dist-info/entry_points.txt
napari_patchcreator-0.1.4.dist-info/top_level.txt
napari_patchcreator-0.1.4.dist-info/RECORD
