Metadata-Version: 2.1
Name: napari-patchcreator
Version: 0.1.4
Summary: A simple plugin to use with napari
Home-page: https://github.com/juglab/napari-patchcreator
Author: Tom Burke
Author-email: burke@mpi-cbg.de
License: BSD-3-Clause
Project-URL: Bug Tracker, https://github.com/juglab/napari-patchcreator/issues
Project-URL: Documentation, https://github.com/juglab/napari-patchcreator#README.md
Project-URL: Source Code, https://github.com/juglab/napari-patchcreator
Project-URL: User Support, https://github.com/juglab/napari-patchcreator/issues
Classifier: Development Status :: 5 - Production/Stable
Classifier: Framework :: napari
Classifier: Intended Audience :: Developers
Classifier: License :: OSI Approved :: BSD License
Classifier: Operating System :: OS Independent
Classifier: Programming Language :: Python
Classifier: Programming Language :: Python :: 3
Classifier: Programming Language :: Python :: 3 :: Only
Classifier: Programming Language :: Python :: 3.8
Classifier: Programming Language :: Python :: 3.9
Classifier: Programming Language :: Python :: 3.10
Classifier: Topic :: Scientific/Engineering :: Image Processing
Requires-Python: >=3.8
License-File: LICENSE
Requires-Dist: numpy
Requires-Dist: napari
Requires-Dist: napari-plugin-engine (>=0.1.4)
Provides-Extra: testing
Requires-Dist: tox ; extra == 'testing'
Requires-Dist: pytest ; extra == 'testing'
Requires-Dist: pytest-cov ; extra == 'testing'
Requires-Dist: pytest-qt ; extra == 'testing'
Requires-Dist: napari ; extra == 'testing'
Requires-Dist: pyqt5 ; extra == 'testing'
